mcts_solver/__init__.py
mcts_solver/mcts_solver.py
mcts_solver-0.0.5.dist-info/LICENSE
mcts_solver-0.0.5.dist-info/METADATA
mcts_solver-0.0.5.dist-info/WHEEL
mcts_solver-0.0.5.dist-info/top_level.txt
mcts_solver-0.0.5.dist-info/RECORD
