Metadata-Version: 2.1
Name: mcts-solver
Version: 0.0.5
Summary: Monte-Carlo tree search solver for chess-ant
Home-page: https://github.com/akuroiwa/mcts-solver
Author: Akihiro Kuroiwa
Author-email: akuroiwa@env-reform.com
License: GNU/GPLv3+
Keywords: mcts,monte,carlo,tree,search,solver
Platform: any
Classifier: Development Status :: 3 - Alpha
Classifier: Environment :: Console
Classifier: Intended Audience :: Developers
Classifier: Intended Audience :: Science/Research
Classifier: Intended Audience :: Education
Classifier: Operating System :: OS Independent
Classifier: License :: OSI Approved :: GNU General Public License v3 or later (GPLv3+)
Classifier: Programming Language :: Python :: 3 :: Only
Classifier: Programming Language :: Python :: 3.7
Classifier: Topic :: Scientific/Engineering
Classifier: Topic :: Scientific/Engineering :: Artificial Intelligence
Classifier: Topic :: Software Development
Classifier: Topic :: Software Development :: Libraries
Classifier: Topic :: Software Development :: Libraries :: Python Modules
Requires-Python: >=3.7
License-File: LICENSE
Requires-Dist: mcts
